cdl_convert/__init__.py
cdl_convert/base.py
cdl_convert/cdl_convert.py
cdl_convert/collection.py
cdl_convert/config.py
cdl_convert/correction.py
cdl_convert/decision.py
cdl_convert/parse.py
cdl_convert/utils.py
cdl_convert/write.py
cdl_convert-0.9.2.dist-info/DESCRIPTION.rst
cdl_convert-0.9.2.dist-info/entry_points.txt
cdl_convert-0.9.2.dist-info/METADATA
cdl_convert-0.9.2.dist-info/metadata.json
cdl_convert-0.9.2.dist-info/RECORD
cdl_convert-0.9.2.dist-info/top_level.txt
cdl_convert-0.9.2.dist-info/WHEEL
