Metadata-Version: 2.0
Name: cdl-convert
Version: 0.9.2
Summary: Converts between common ASC Color Decision List (CDL) formats
Home-page: http://github.com/shidarin/cdl_convert
Author: Sean Wallitsch
Author-email: shidarin@alphamatte.com
License: MIT
Keywords: film tv color conversion converter cdl editing
Platform: any
Classifier: Development Status :: 4 - Beta
Classifier: Intended Audience :: End Users/Desktop
Classifier: Intended Audience :: Developers
Classifier: Topic :: Multimedia :: Graphics
Classifier: Topic :: Multimedia :: Video
Classifier: Topic :: Multimedia :: Video :: Display
Classifier: Topic :: Multimedia :: Video :: Non-Linear Editor
Classifier: Topic :: Software Development :: Libraries :: Python Modules
Classifier: License :: OSI Approved :: MIT License
Classifier: Programming Language :: Python :: 2
Classifier: Programming Language :: Python :: 2.6
Classifier: Programming Language :: Python :: 2.7
Classifier: Programming Language :: Python :: 3
Classifier: Programming Language :: Python :: 3.1
Classifier: Programming Language :: Python :: 3.2
Classifier: Programming Language :: Python :: 3.3
Classifier: Programming Language :: Python :: 3.4
Classifier: Programming Language :: Python :: Implementation :: CPython
Classifier: Programming Language :: Python :: Implementation :: PyPy
Classifier: Operating System :: OS Independent
Classifier: Natural Language :: English
